qjer/__init__.py
qjer/ngw.py
qjer/bike/__init__.py
qjer/bike/bike0.py
qjer/bike/bike1.py
qjer/bike/bike2.py
qjer/bike/bike3.py
qjer/bike/bike4.py
qjer/bike/bike5.py
qjer/bike/bike6.py
qjer/bike/bike7.py
qjer/internetloganalysis/__init__.py
qjer/internetloganalysis/internetlogs/__init__.py
qjer/internetloganalysis/internetlogs/browser.py
qjer/internetloganalysis/internetlogs/ip.py
qjer/internetloganalysis/internetlogs/pv.py
qjer/internetloganalysis/internetlogs/time.py
qjer/internetloganalysis/retrievelog/__init__.py
qjer/internetloganalysis/retrievelog/behavior.py
qjer/internetloganalysis/retrievelog/key.py
qjer/internetloganalysis/retrievelog/rank.py
qjer/internetloganalysis/retrievelog/time.py
qjer/internetloganalysis/retrievelog/url.py
qjer/jichuhuanjing/__init__.py
qjer/jichuhuanjing/bigdata.py
qjer/luntan/__init__.py
qjer/luntan/data.py
qjer/luntan/lt_operator.py
qjer/luntan/pazhong.py
qjer/python_demo/__init__.py
qjer/python_demo/damixiaoliang.py
qjer/python_demo/ershoufang.py
qjer/python_demo/jisuanjinggaimianji.py
qjer/python_demo/jiujiu.py
qjer/python_demo/sandiantu.py
qjer/python_demo/wuliufenxi.py
qjer/python_demo/xiaoshou.py
qjer/python_demo/yichangdian.py
qjer/python_demo/zuiyoucaigoufangan.py
qjer/shangcheng/__init__.py
qjer/shangcheng/sc_operator.py
qjer/shangcheng/spider.py
qjer/spark/Analysis.py
qjer/spark/HadoopFileIoAdapter.py
qjer/spark/NetCount1.py
qjer/spark/NetCount2.py
qjer/spark/NetCount3.py
qjer/spark/NetCount4.py
qjer/spark/NetCount5.py
qjer/spark/NetCount6.py
qjer/spark/UserUtils.py
qjer/spark/WebLogAn.py
qjer/spark/WordSegment.py
qjer/spark/WordSegmentTDIDF.py
qjer/spark/__init__.py
qjer/spark/pom.py
qjer/stream/__init__.py
qjer/stream/main.py
qjer-1.0.dist-info/LICENSE
qjer-1.0.dist-info/METADATA
qjer-1.0.dist-info/WHEEL
qjer-1.0.dist-info/top_level.txt
qjer-1.0.dist-info/RECORD
