Metadata-Version: 2.1
Name: qjer
Version: 1.0
Summary: 一个很NB的包
Home-page: 
Author: ngw
Author-email: 821512128@qq.com
Classifier: Programming Language :: Python :: 3
Classifier: License :: OSI Approved :: MIT License
Requires-Python: >=3
License-File: LICENSE
